tegen/__init__.py
tegen/game.py
tegen/objects.py
tegen/pixel.py
tegen/scene.py
tegen/examples/tictactoe.py
tegen-0.0.dist-info/LICENSE
tegen-0.0.dist-info/METADATA
tegen-0.0.dist-info/WHEEL
tegen-0.0.dist-info/top_level.txt
tegen-0.0.dist-info/RECORD
