Metadata-Version: 2.1
Name: tegen
Version: 0.0
Summary: Terminal game engine for Python
Home-page: https://github.com/iiiii7d/tegen
Author: 7d
Author-email: i.third.7d@protonmail.com
License: gpl-3.0
Download-URL: https://github.com/iiiii7d/tegen/archive/refs/tags/v0.0.tar.gz
Keywords: tegen,terminal,game,engine,terminal game engine,game development
Platform: UNKNOWN
Classifier: Development Status :: 4 - Beta
Classifier: Intended Audience :: Developers
Classifier: Intended Audience :: End Users/Desktop
Classifier: License :: OSI Approved :: GNU General Public License v3 (GPLv3)
Classifier: Natural Language :: English
Classifier: Programming Language :: Python
Classifier: Programming Language :: Python :: 3
Classifier: Programming Language :: Python :: 3.6
Classifier: Programming Language :: Python :: 3.7
Classifier: Programming Language :: Python :: 3.8
Classifier: Programming Language :: Python :: 3.9
Classifier: Topic :: Games/Entertainment
Requires-Python: >=3.6, <3.10
Requires-Dist: blessed
Requires-Dist: wcwidth
Requires-Dist: pillow
